cna/__init__.py
cna/plotting/__init__.py
cna/plotting/_strat.py
cna/plotting/_umap.py
cna/tools/__init__.py
cna/tools/_association.py
cna/tools/_nam.py
cna/tools/_out.py
cna/tools/_stats.py
cna/utils/__init__.py
cna/utils/multisample.py
cna-0.2.2.dist-info/licenses/LICENSE
cna-0.2.2.dist-info/METADATA
cna-0.2.2.dist-info/WHEEL
cna-0.2.2.dist-info/top_level.txt
cna-0.2.2.dist-info/RECORD
