Metadata-Version: 2.4
Name: cna
Version: 0.2.2
Summary: covarying neighborhood analysis
Home-page: https://github.com/immunogenomics/cna
Author: Yakir Reshef, Laurie Rumker
Author-email: yreshef@broadinstitute.org, lrumker@broadinstitute.org
Project-URL: Bug Tracker, https://github.com/immunogenomics/cna/issues
Project-URL: Tutorial, https://github.com/immunogenomics/cna/blob/master/demo/demo.ipynb
Classifier: Programming Language :: Python :: 3
Classifier: License :: OSI Approved :: MIT License
Classifier: Operating System :: OS Independent
Requires-Python: >=3.6
License-File: LICENSE
Requires-Dist: anndata>=0.7.1
Requires-Dist: numpy>=1.18.1
Requires-Dist: pandas>=1.0.3
Requires-Dist: scipy>=1.4.1
Requires-Dist: argparse>=1.1
Requires-Dist: matplotlib>=3.1.3
Requires-Dist: scanpy>=1.4.4.post1
Dynamic: license-file
